lab2/P3/two_bit_4to1muxV2.v
module two_bit_4to1muxV2 (s,u,v,w,x,m);
 
	input[1:0] s;
	input[1:0] u,v,w,x;
	output reg[1:0] m;
	
	reg[1:0] t1, t2;
	
	//complete always blocks (look at one_bit_4to1muxV2.v for hints. Should look the same)
	always @(s[0], u, v) begin
		if(s[0] == 1) begin t1 = v; end
		else begin t1 = u; end
	end
	always @(s[0], w, x) begin
		if(s[0] == 1) begin t2 = x; end
		else begin t2 = w; end
	end

	always @(s[1], t1, t2) begin
		if(s[1] == 1) begin m = t2; end
		else begin m = t1; end
	end

endmodule

lab2/P3/part3_TB.v
`timescale 1ns / 1ps
 
module part3_TB;
 
	// ------------------ Instantiate module ------------------
	// We are instantiating the module mux2, naming it instantiate_mux2.
	// select, input1, input2 are controlled by the testbench, output is 
	// checked  within the testbench
 
	reg [3:0] count;
	reg [1:0] select;
	reg [1:0] input1, input2, input3, input4;
	wire [1:0] output1;
	
	two_bit_4to1muxV2 instantiate_mux4_2bit(.s(select),.u(input1),.v(input2),.w(input3),.x(input4),.m(output1));

	initial begin
		$dumpfile("testbench1.vcd");
		$dumpvars(0, part3_TB);
		#600;
		$finish;
	end


	initial begin 
		count = 4'b0000;
	end
	
	always begin
		#50
		count=count+4'b0001;
	end
	
	always @(count) begin
		case (count)
		4'b0000 : begin input1 = 2'b01; input2 = 2'b00; input3 = 2'b00; input4 = 2'b00; select = 2'b00; end
		4'b0001 : begin input1 = 2'b01; input2 = 2'b00; input3 = 2'b00; input4 = 2'b00; select = 2'b01; end
		4'b0010 : begin input1 = 2'b01; input2 = 2'b00; input3 = 2'b00; input4 = 2'b00; select = 2'b10; end
		4'b0011 : begin input1 = 2'b01; input2 = 2'b00; input3 = 2'b00; input4 = 2'b00; select = 2'b11; end
		4'b0100 : begin input1 = 2'b00; input2 = 2'b01; input3 = 2'b00; input4 = 2'b00; select = 2'b00; end
		4'b0101 : begin input1 = 2'b00; input2 = 2'b01; input3 = 2'b00; input4 = 2'b00; select = 2'b01; end
		4'b0110 : begin input1 = 2'b00; input2 = 2'b01; input3 = 2'b00; input4 = 2'b00; select = 2'b10; end
		4'b0111 : begin input1 = 2'b00; input2 = 2'b01; input3 = 2'b00; input4 = 2'b00; select = 2'b11; end
		4'b1000 : begin input1 = 2'b00; input2 = 2'b01; input3 = 2'b10; input4 = 2'b00; select = 2'b01; end
		4'b1001 : begin input1 = 2'b00; input2 = 2'b01; input3 = 2'b10; input4 = 2'b00; select = 2'b10; end
		4'b1010 : begin input1 = 2'b00; input2 = 2'b11; input3 = 2'b10; input4 = 2'b00; select = 2'b01; end
		default : begin input1 = 2'b00; input2 = 2'b00; input3 = 2'b00; input4 = 2'b00; select = 2'b00; end
	endcase
	end

 
endmodule

lab2/P3/testbench1.vcd
$date
	Thu Mar 12 13:15:54 2026
$end
$version
	Icarus Verilog
$end
$timescale
	1ps
$end
$scope module part3_TB $end
$var wire 2 ! output1 [1:0] $end
$var reg 4 " count [3:0] $end
$var reg 2 # input1 [1:0] $end
$var reg 2 $ input2 [1:0] $end
$var reg 2 % input3 [1:0] $end
$var reg 2 & input4 [1:0] $end
$var reg 2 ' select [1:0] $end
$scope module instantiate_mux4_2bit $end
$var wire 2 ( s [1:0] $end
$var wire 2 ) u [1:0] $end
$var wire 2 * v [1:0] $end
$var wire 2 + w [1:0] $end
$var wire 2 , x [1:0] $end
$var reg 2 - m [1:0] $end
$var reg 2 . t1 [1:0] $end
$var reg 2 / t2 [1:0] $end
$upscope $end
$upscope $end
$enddefinitions $end
$comment Show the parameter values. $end
$dumpall
$end
#0
$dumpvars
b0 /
b1 .
b1 -
b0 ,
b0 +
b0 *
b1 )
b0 (
b0 '
b0 &
b0 %
b0 $
b1 #
b0 "
b1 !
$end
#50000
b0 !
b0 -
b0 .
b1 '
b1 (
b1 "
#100000
b1 .
b10 '
b10 (
b10 "
#150000
b0 .
b11 '
b11 (
b11 "
#200000
b0 '
b0 (
b1 $
b1 *
b0 #
b0 )
b100 "
#250000
b1 !
b1 -
b1 .
b1 '
b1 (
b101 "
#300000
b0 .
b0 !
b0 -
b10 '
b10 (
b110 "
#350000
b1 .
b11 '
b11 (
b111 "
#400000
b1 !
b1 -
b1 '
b1 (
b10 %
b10 +
b1000 "
#450000
b0 .
b10 /
b10 !
b10 -
b10 '
b10 (
b1001 "
#500000
b0 /
b11 !
b11 -
b11 .
b1 '
b1 (
b11 $
b11 *
b1010 "
#550000
b0 !
b0 -
b0 .
b0 '
b0 (
b0 %
b0 +
b0 $
b0 *
b1011 "
#600000
b1100 "
